{
  "annotations": {
    "list": [
      {
        "builtIn": 1,
        "datasource": "-- Grafana --",
        "enable": true,
        "hide": true,
        "iconColor": "rgba(0, 211, 255, 1)",
        "name": "Annotations & Alerts",
        "type": "dashboard"
      }
    ]
  },
  "description": "This dashboard is a visualization for the algorithm described at https://docs.gitlab.com/runner/configuration/autoscale.html. Look on it as for a replacement for this graph: https://docs.gitlab.com/runner/configuration/img/autoscale-example.png from the documentation page.",
  "editable": true,
  "gnetId": null,
  "graphTooltip": 1,
  "id": null,
  "iteration": 1617917755888,
  "links": [

  ],
  "panels": [
    {
      "content": "This dashboard is a visualization for the algorithm described at https://docs.gitlab.com/runner/configuration/autoscale.html.\n\nLook on it as for a replacement for this graph - https://docs.gitlab.com/runner/configuration/img/autoscale-example.png - from the documentation page.\n\n\n\n",
      "datasource": null,
      "fieldConfig": {
        "defaults": {
          "custom": {
          }
        },
        "overrides": [

        ]
      },
      "gridPos": {
        "h": 6,
        "w": 24,
        "x": 0,
        "y": 0
      },
      "id": 4,
      "mode": "markdown",
      "options": {
        "content": "# Outdated\n\nThe dashboard is outdated and not maintained anymore.\n\nA replacement for it can be found at https://dashboards.gitlab.net/d/ci-runners-autoscaling-algorithm/ci-runners-autoscaling-algorithm\n\n---\n\nThis dashboard is a visualization for the algorithm described at https://docs.gitlab.com/runner/configuration/autoscale.html.\n\nLook on it as for a replacement for this graph - https://docs.gitlab.com/runner/configuration/img/autoscale-example.png - from the documentation page.\n\n\n\n",
        "mode": "markdown"
      },
      "pluginVersion": "7.1.0",
      "timeFrom": null,
      "timeShift": null,
      "title": "",
      "transparent": true,
      "type": "text"
    },
    {
      "aliasColors": {
      },
      "bars": false,
      "dashLength": 10,
      "dashes": false,
      "datasource": null,
      "fieldConfig": {
        "defaults": {
          "custom": {
          },
          "links": [

          ]
        },
        "overrides": [

        ]
      },
      "fill": 0,
      "fillGradient": 0,
      "gridPos": {
        "h": 17,
        "w": 24,
        "x": 0,
        "y": 6
      },
      "hiddenSeries": false,
      "id": 2,
      "legend": {
        "alignAsTable": true,
        "avg": true,
        "current": true,
        "max": true,
        "min": true,
        "rightSide": true,
        "show": true,
        "total": false,
        "values": true
      },
      "lines": true,
      "linewidth": 1,
      "links": [

      ],
      "nullPointMode": "null",
      "options": {
        "alertThreshold": true
      },
      "percentage": false,
      "pluginVersion": "7.2.0",
      "pointradius": 2,
      "points": false,
      "renderer": "flot",
      "seriesOverrides": [
        {
          "$$hashKey": "object:56",
          "alias": "Number of running jobs",
          "color": "rgb(255, 255, 255)",
          "linewidth": 5,
          "zindex": -3
        },
        {
          "$$hashKey": "object:57",
          "alias": "Number of existing machines",
          "color": "#1F60C4",
          "linewidth": 3
        },
        {
          "$$hashKey": "object:58",
          "alias": "Number of creating machines",
          "pointradius": 1,
          "points": true
        },
        {
          "$$hashKey": "object:59",
          "alias": "Number of removing machines",
          "pointradius": 1,
          "points": true
        },
        {
          "$$hashKey": "object:60",
          "alias": "Number of used machines",
          "linewidth": 2
        },
        {
          "$$hashKey": "object:61",
          "alias": "Number of idle machines",
          "linewidth": 2
        },
        {
          "$$hashKey": "object:138",
          "alias": "Limit utilization",
          "color": "rgba(200, 242, 194, 0.85)",
          "fill": 1,
          "yaxis": 2,
          "zindex": -2
        }
      ],
      "spaceLength": 10,
      "stack": false,
      "steppedLine": false,
      "targets": [
        {
          "expr": "sum(gitlab_runner_jobs{instance=~\"${runner_managers:pipe}\", instance=~\"${runner_managers:pipe}\"})",
          "format": "time_series",
          "interval": "",
          "intervalFactor": 4,
          "legendFormat": "Number of running jobs",
          "refId": "C"
        },
        {
          "expr": "sum(gitlab_runner_autoscaling_machine_states{state=~\"idle|used|creating|removing\", executor=\"docker+machine\", instance=~\"${runner_managers:pipe}\"}) by (state)",
          "format": "time_series",
          "interval": "",
          "intervalFactor": 4,
          "legendFormat": "Number of {{state}} machines",
          "refId": "B"
        },
        {
          "expr": "sum(gitlab_runner_autoscaling_machine_states{state=~\"idle|used|creating|removing\", executor=\"docker+machine\", instance=~\"${runner_managers:pipe}\"})",
          "format": "time_series",
          "interval": "",
          "intervalFactor": 4,
          "legendFormat": "Number of existing machines",
          "refId": "A"
        },
        {
          "expr": "sum(gitlab_runner_jobs{instance=~\"${runner_managers:pipe}\"}) / sum(gitlab_runner_limit{instance=~\"${runner_managers:pipe}\"}) ",
          "interval": "",
          "intervalFactor": 4,
          "legendFormat": "Limit utilization",
          "refId": "D"
        }
      ],
      "thresholds": [

      ],
      "timeFrom": null,
      "timeRegions": [

      ],
      "timeShift": null,
      "title": "Autoscaling algorithm",
      "tooltip": {
        "shared": true,
        "sort": 2,
        "value_type": "individual"
      },
      "type": "graph",
      "xaxis": {
        "buckets": null,
        "mode": "time",
        "name": null,
        "show": true,
        "values": [

        ]
      },
      "yaxes": [
        {
          "$$hashKey": "object:108",
          "format": "short",
          "label": null,
          "logBase": 1,
          "max": null,
          "min": null,
          "show": true
        },
        {
          "$$hashKey": "object:109",
          "format": "percentunit",
          "label": null,
          "logBase": 1,
          "max": null,
          "min": null,
          "show": true
        }
      ],
      "yaxis": {
        "align": true,
        "alignLevel": null
      }
    },
    {
      "collapsed": true,
      "datasource": null,
      "gridPos": {
        "h": 1,
        "w": 24,
        "x": 0,
        "y": 23
      },
      "id": 7,
      "panels": [
        {
          "aliasColors": {
          },
          "bars": false,
          "dashLength": 10,
          "dashes": false,
          "datasource": null,
          "fieldConfig": {
            "defaults": {
              "custom": {
              },
              "links": [

              ]
            },
            "overrides": [

            ]
          },
          "fill": 0,
          "fillGradient": 0,
          "gridPos": {
            "h": 17,
            "w": 24,
            "x": 0,
            "y": 21
          },
          "hiddenSeries": false,
          "id": 5,
          "legend": {
            "alignAsTable": true,
            "avg": true,
            "current": true,
            "max": true,
            "min": true,
            "rightSide": false,
            "show": true,
            "total": false,
            "values": true
          },
          "lines": true,
          "linewidth": 1,
          "links": [

          ],
          "nullPointMode": "null",
          "options": {
            "alertThreshold": true
          },
          "percentage": false,
          "pluginVersion": "7.2.0",
          "pointradius": 2,
          "points": false,
          "renderer": "flot",
          "seriesOverrides": [
            {
              "$$hashKey": "object:228",
              "alias": "Number of all machines excluting idle",
              "color": "#8AB8FF",
              "linewidth": 2,
              "yaxis": 2,
              "zindex": -3
            },
            {
              "$$hashKey": "object:229",
              "alias": "Idle per used machines",
              "color": "#C4162A"
            },
            {
              "$$hashKey": "object:230",
              "alias": "Number of idle machines",
              "color": "#96D98D",
              "linewidth": 2,
              "yaxis": 2,
              "zindex": -3
            }
          ],
          "spaceLength": 10,
          "stack": false,
          "steppedLine": false,
          "targets": [
            {
              "expr": "sum(gitlab_runner_autoscaling_machine_states{state=\"idle\", executor=\"docker+machine\", instance=~\"${runner_managers:pipe}\"})\n/\nsum(gitlab_runner_autoscaling_machine_states{state=\"used\", executor=\"docker+machine\", instance=~\"${runner_managers:pipe}\"})",
              "format": "time_series",
              "hide": false,
              "intervalFactor": 4,
              "legendFormat": "Idle per used machines",
              "refId": "B"
            },
            {
              "expr": "sum(gitlab_runner_autoscaling_machine_states{state=~\"used|creating|removing\", executor=\"docker+machine\", instance=~\"${runner_managers:pipe}\"})",
              "interval": "",
              "intervalFactor": 4,
              "legendFormat": "Number of all machines excluting idle",
              "refId": "A"
            },
            {
              "expr": "sum(gitlab_runner_autoscaling_machine_states{state=\"idle\", executor=\"docker+machine\", instance=~\"${runner_managers:pipe}\"})",
              "interval": "",
              "intervalFactor": 4,
              "legendFormat": "Number of idle machines",
              "refId": "C"
            }
          ],
          "thresholds": [
            {
              "$$hashKey": "object:1052",
              "colorMode": "warning",
              "fill": true,
              "fillColor": "rgba(50, 116, 217, 0.2)",
              "line": true,
              "lineColor": "rgba(31, 96, 196, 0.6)",
              "op": "gt",
              "value": 1,
              "yaxis": "left"
            }
          ],
          "timeFrom": null,
          "timeRegions": [

          ],
          "timeShift": null,
          "title": "Relation of idle per used machines",
          "tooltip": {
            "shared": true,
            "sort": 2,
            "value_type": "individual"
          },
          "type": "graph",
          "xaxis": {
            "buckets": null,
            "mode": "time",
            "name": null,
            "show": true,
            "values": [

            ]
          },
          "yaxes": [
            {
              "$$hashKey": "object:643",
              "format": "percentunit",
              "label": null,
              "logBase": 1,
              "max": null,
              "min": null,
              "show": true
            },
            {
              "$$hashKey": "object:644",
              "format": "short",
              "label": null,
              "logBase": 1,
              "max": null,
              "min": null,
              "show": true
            }
          ],
          "yaxis": {
            "align": false,
            "alignLevel": null
          }
        }
      ],
      "title": "idle/used",
      "type": "row"
    }
  ],
  "refresh": false,
  "schemaVersion": 26,
  "style": "dark",
  "tags": [
    "ci",
    "unmanaged"
  ],
  "templating": {
    "list": [
      {
        "allValue": null,
        "current": {
          "selected": true,
          "tags": [

          ],
          "text": [
            "All"
          ],
          "value": [
            "$__all"
          ]
        },
        "datasource": "Global",
        "definition": "label_values(gitlab_runner_autoscaling_machine_states{job=\"runners-manager\",shard!~\"(default|windows-shared)\"}, shard)",
        "hide": 0,
        "includeAll": true,
        "label": "Shard",
        "multi": true,
        "name": "shard",
        "options": [

        ],
        "query": "label_values(gitlab_runner_autoscaling_machine_states{job=\"runners-manager\",shard!~\"(default|windows-shared)\"}, shard)",
        "refresh": 1,
        "regex": "",
        "skipUrlSync": false,
        "sort": 1,
        "tagValuesQuery": "",
        "tags": [

        ],
        "tagsQuery": "",
        "type": "query",
        "useTags": false
      },
      {
        "allValue": null,
        "current": {
          "selected": true,
          "text": [
            "All"
          ],
          "value": [
            "$__all"
          ]
        },
        "datasource": "Global",
        "definition": "query_result(label_replace(gitlab_runner_version_info{shard=~\"$shard\"}, \"fqdn\", \"$1.*\", \"instance\", \"(.*):[0-9]+$\"))",
        "hide": 0,
        "includeAll": true,
        "label": "Runner Managers",
        "multi": true,
        "name": "runner_managers",
        "options": [

        ],
        "query": "query_result(label_replace(gitlab_runner_version_info{shard=~\"$shard\"}, \"fqdn\", \"$1.*\", \"instance\", \"(.*):[0-9]+$\"))",
        "refresh": 1,
        "regex": "/fqdn=\"([^\"]+)\"/",
        "skipUrlSync": false,
        "sort": 1,
        "tagValuesQuery": "",
        "tags": [

        ],
        "tagsQuery": "",
        "type": "query",
        "useTags": false
      }
    ]
  },
  "time": {
    "from": "now-3h",
    "to": "now"
  },
  "timepicker": {
    "refresh_intervals": [
      "5s",
      "10s",
      "30s",
      "1m",
      "5m",
      "15m",
      "30m",
      "1h",
      "2h",
      "1d"
    ],
    "time_options": [
      "5m",
      "15m",
      "1h",
      "6h",
      "12h",
      "24h",
      "2d",
      "7d",
      "30d"
    ]
  },
  "timezone": "utc",
  "title": "CI - autoscaling algorithm visualisation",
  "uid": "r9NUva5Wk",
  "version": 17
}