{"meta":{"type":"db","canSave":false,"canEdit":false,"canAdmin":false,"canStar":true,"slug":"reboots","url":"/d/yzukVGtZz/reboots","expires":"0001-01-01T00:00:00Z","created":"2019-09-18T05:33:48Z","updated":"2020-06-11T13:12:47Z","updatedBy":"ops-contact@gitlab.com","createdBy":"ops-contact@gitlab.com","version":8,"hasAcl":false,"isFolder":false,"folderId":1299,"folderTitle":"SRE Personal Dashboards","folderUrl":"/dashboards/f/K8JDABmGk/sre-personal-dashboards","provisioned":false,"provisionedExternalId":""},"dashboard":{"annotations":{"list":[{"builtIn":1,"datasource":"-- Grafana --","enable":true,"hide":true,"iconColor":"rgba(0, 211, 255, 1)","name":"Annotations \u0026 Alerts","type":"dashboard"}]},"editable":true,"gnetId":null,"graphTooltip":0,"id":null,"links":[],"panels":[{"aliasColors":{},"bars":true,"dashLength":10,"dashes":false,"datasource":null,"fill":1,"fillGradient":0,"gridPos":{"h":21,"w":24,"x":0,"y":0},"id":2,"legend":{"avg":false,"current":false,"max":false,"min":false,"show":true,"total":false,"values":false},"lines":false,"linewidth":1,"links":[],"nullPointMode":"null","options":{"dataLinks":[]},"percentage":false,"pointradius":2,"points":false,"renderer":"flot","seriesOverrides":[],"spaceLength":10,"stack":false,"steppedLine":false,"targets":[{"expr":"changes(node_boot_time_seconds{env=\"$env\",monitor=\"$monitor\"}[$__interval]) \u003e 0","format":"time_series","hide":true,"interval":"10m","intervalFactor":10,"legendFormat":"{{instance}}","refId":"B"},{"expr":"clamp_max(abs(delta(node_boot_time_seconds{env=\"$env\",monitor=\"$monitor\"}[$__interval])) \u003e 10, 1)","interval":"10m","intervalFactor":10,"legendFormat":"{{instance}}","refId":"A"}],"thresholds":[],"timeFrom":null,"timeRegions":[],"timeShift":null,"title":"Reboots","tooltip":{"shared":true,"sort":0,"value_type":"individual"},"type":"graph","xaxis":{"buckets":null,"mode":"time","name":null,"show":true,"values":[]},"yaxes":[{"format":"short","label":null,"logBase":1,"max":null,"min":"0","show":true},{"format":"short","label":null,"logBase":1,"max":null,"min":null,"show":true}],"yaxis":{"align":false,"alignLevel":null}}],"refresh":false,"schemaVersion":22,"style":"dark","tags":[],"templating":{"list":[{"allValue":null,"current":{"text":"gprd","value":"gprd"},"datasource":"Global","definition":"label_values(node_boot_time_seconds, env)","hide":0,"includeAll":false,"label":null,"multi":false,"name":"env","options":[],"query":"label_values(node_boot_time_seconds, env)","refresh":1,"regex":"","skipUrlSync":false,"sort":0,"tagValuesQuery":"","tags":[],"tagsQuery":"","type":"query","useTags":false},{"allValue":null,"current":{"text":"default","value":"default"},"datasource":"Global","definition":"label_values(node_boot_time_seconds{env=\"$env\"}, monitor)","hide":0,"includeAll":false,"label":null,"multi":false,"name":"monitor","options":[],"query":"label_values(node_boot_time_seconds{env=\"$env\"}, monitor)","refresh":2,"regex":"","skipUrlSync":false,"sort":0,"tagValuesQuery":"","tags":[],"tagsQuery":"","type":"query","useTags":false}]},"time":{"from":"now-7d","to":"now"},"timepicker":{"refresh_intervals":["5s","10s","30s","1m","5m","15m","30m","1h","2h","1d"],"time_options":["5m","15m","1h","6h","12h","24h","2d","7d","30d"]},"timezone":"","title":"Reboots","uid":"yzukVGtZz","variables":{"list":[]},"version":8}}